modrinth_downloader/__init__.py
modrinth_downloader/api.py
modrinth_downloader/downloader.py
modrinth_downloader/utils.py
modrinth_downloader/scripts/__init__.py
modrinth_downloader/scripts/config.toml
modrinth_downloader/scripts/run_downloader.py
tests/__init__.py
tests/test_downloader.py
modrinth_downloader-0.9.5.dist-info/METADATA
modrinth_downloader-0.9.5.dist-info/WHEEL
modrinth_downloader-0.9.5.dist-info/entry_points.txt
modrinth_downloader-0.9.5.dist-info/top_level.txt
modrinth_downloader-0.9.5.dist-info/RECORD
