Metadata-Version: 2.1
Name: modrinth-downloader
Version: 0.9.5
Summary: Download projects from Modrinth
Author: Alexander Brightwater
Classifier: Programming Language :: Python :: 3
Classifier: License :: OSI Approved :: MIT License
Classifier: Operating System :: OS Independent
Requires-Python: >=3.11
Requires-Dist: argparse
Requires-Dist: requests
Requires-Dist: toml
